<?xml version="1.0" ?>
<annotation>
	<videoname>java-1</videoname>
	<box>
		<pos>02536</pos>
	</box>
	<bndbox>
		<xmin>36</xmin>
		<ymin>195</ymin>
		<xmax>532</xmax>
		<ymax>253</ymax>
	</bndbox>
	<bndbox>
		<xmin>22</xmin>
		<ymin>217</ymin>
		<xmax>33</xmax>
		<ymax>237</ymax>
	</bndbox>
	<max_box>
		<xmin>36</xmin>
		<ymin>195</ymin>
		<xmax>532</xmax>
		<ymax>253</ymax>
	</max_box>
	<max_region>
		<xmin>22</xmin>
		<ymin>195</ymin>
		<xmax>532</xmax>
		<ymax>253</ymax>
	</max_region>
</annotation>
